Workbook

Sheet iNaturalist_Experts_US_Canada
A1: Name | B1: iNaturalist_username | C1: iNaturalist_name | D1: iNaturalist_id | E1: NatureServe Network Staff Status | F1: Organization | G1: Title | H1: Taxonomic Expertise | I1: Expertise LU | J1: Comments on Taxonomic Expertise | K1: Region of Expertise | L1: Source (past efforts or name and email) | M1: No_Observations | N1: No_Identifications | O1: No_Species | P1: Curator
A2: Alexandre Anctil | B2: a_anctil | D2: 1381960 | E2: No | F2: Quebec CDC | G2: Coordonnator - fauna component | H2: Vertebrates|Birds | I2: A% | K2: NB, NS, PE | L2: Canadian Node Expert List | M2: 18289 | N2: 24311 | O2: 2030
A3: Andrea Benville | B3: a_b | C3: Andrea Benville | D3: 35013 | E3: Current | F3: Saskatchewan Conservation Data Centre | L3: 2020 network survey on iNaturalist | M3: 845 | N3: 870 | O3: 471
A4: Alison Smith | B4: a_smith | C4: Alison Smith | D4: 1340454 | E4: Current | F4: Ontario Natural Heritage Information Centre | G4: Natural Heritage Zoologist | L4: NatureServe Network Staff List | M4: 7213 | N4: 5416 | O4: 1941
A5: Aaron Liston | B5: aaronliston | C5: Aaron Liston | D5: 266181 | E5: No | H5: Vascular Plants, particularly Astragalus | I5: P% | L5: MTNHP Expert List | M5: 3907 | N5: 48819 | O5: 2107 | P5: curator
A6: Aaron Marcus | B6: aaronmarcus | C6: Aaron Marcus | D6: 682499 | E6: Former | H6: Vascular|Non-vascular Plants | I6: P%|NB% | L6: NatureServe Network Staff List | M6: 281 | N6: 60 | O6: 168
A7: Ben Rostron | B7: ab_orchid | D7: 3304841 | E7: No | F7: University of Alberta | G7: Emeritus Professor | H7: Orchidaceae | I7: PMORC% | K7: AB | L7: Canadian Node Expert List and MTNHP Expert List | M7: 399 | N7: 35462 | O7: 30
A8: Robin Abernethy | B8: aber_r16 | C8: Robin Abernethy | D8: 2528838 | E8: Current | F8: Northwest Territories Conservation Data Centre | G8: GIS and Wildlife Data Specialist | L8: NatureServe Network Staff List | M8: 110 | N8: 0 | O8: 82
A9: Andrew Smith | B9: abtsmith | C9: Andrew Smith | D9: 1327158 | E9: No | F9: Canadian Museum of Nature and the University of Nebraska State Museum. | G9: Research Associate | H9: Insects|Coleoptera | I9: II% | J9: Especially Scarabidae | L9: MBP Expert List | M9: 59 | N9: 13981 | O9: 48 | P9: curator
A10: Andrew Christensen | B10: achr2 | C10: Andrew Christensen | D10: 7072130 | E10: Current | F10: Oregon Biodiversity Information Center | G10: Watershed GIS Analyst | H10: Vascular Plants | I10: P% | L10: 2024 Network Survey | M10: 0 | N10: 0 | O10: 0
A11: Amanda Veinotte | B11: acveinotte | C11: Amanda Veinotte | D11: 1122139 | E11: Current | F11: Massachusetts Natural Heritage & Endangered Species Program | G11: Program Coordinator | L11: NatureServe Network Staff List | M11: 98 | N11: 2 | O11: 79
A12: Adam Durocher | B12: adamdurocher | D12: 1387541 | E12: Current | F12: Atlantic Canada Conservation Data Centre | G12: Newfoundland and Labrador Data Manager | L12: NatureServe Network Staff List | M12: 290 | N12: 7 | O12: 210
A13: Alex Dohman | B13: adohman | C13: Alex Dohman | D13: 1297292 | E13: Current | F13: North Dakota Natural Heritage Inventory | G13: Biologist | L13: NatureServe Network Staff List | M13: 136 | N13: 88 | O13: 115
A14: Adam Martin | B14: ady_m | C14: Adam Martin | D14: 11864 | E14: No | F14: Ecostudies Institute | G14: Botanist and Applied Ecologist | H14: Vascular Plants|Mammals | I14: P%|AM% | J14: Ecostudies Institute, Washington | L14: 2024 Network Survey | M14: 1047 | N14: 266 | O14: 441
A15: Ansel Fiddaman | B15: afid | D15: 1254600 | E15: No | H15: Orchidaceae | I15: PMORC% | K15: NF/LB | L15: Canadian Node Expert List and MTNHP Expert List | M15: 3071 | N15: 65876 | O15: 62
A16: Alain Belliveau | B16: agbelliveau | D16: 533332 | E16: No | F16: E.C. Smith Herbarium, Acadia University | G16: Collections Manager | H16: Vascular Plants|Lichens | I16: P%|NL% | K16: YT, NB, NS, PE | L16: Canadian Node Expert List | M16: 1211 | N16: 1495 | O16: 730
A17: Andrew Grosse | B17: agrosse | D17: 3596662 | E17: Current | F17: South Carolina Department of Natural Resources | G17: State Herpetologist | H17: Amphibia|Reptilia | I17: AA%|AR% | J17: SC DNR Herpetologist, 20 years experience, South Carolina | L17: 2024 Network Survey | M17: 0 | N17: 0 | O17: 0
A18: Alejandro Huereca Delgado | B18: ahuereca | C18: Alejandro Huereca Delgado | D18: 683372 | E18: No | F18: University of Alberta | G18: Master's Degree Student huerecad@ualberta.ca | H18: Lichens and Lichenicolous Fungi | I18: NL% | K18: Mostly Mexico | L18: Denny Bohmer; umbohmer@gmail.com | M18: 6002 | N18: 17343 | O18: 2273 | P18: curator
A19: Arturo Santos | B19: aispinsects | C19: Arturo Santos | D19: 604948 | E19: No | H19: Diptera, particularly Anthomyiidae|Orthoptera | I19: IIDIP%|IIORT% | J19: Primary expertise with insects of central Florida peninsula and New York. | L19: 2024 Network Survey | M19: 4173 | N19: 50188 | O19: 1955 | P19: curator
A20: Amy Jewitt | B20: ajewitt | C20: Amy Jewitt | D20: 16288 | E20: Current | F20: Pennsylvania Natural Heritage Program | G20: Invasive Species Coordinator | H20: Invasive species | I20: P%|A%|I% | L20: NatureServe Network Staff List | M20: 92 | N20: 13 | O20: 66
A21: Allan Trently | B21: ajtrently | C21: Trently,Allan J | D21: 29618 | E21: Current | F21: Tennessee Division of Natural Areas | G21: Stewardship Ecologist (West TN) | L21: NatureServe Network Staff List | M21: 4723 | N21: 473 | O21: 2271
A22: Alex Wright | B22: ajwright | C22: Alex Wright | D22: 205278 | E22: No | F22: Bellevue Botanical Garden | G22: Curator | H22: Vascular Plants | I22: P% | K22: NB, NS, PE | L22: MTNHP Expert List and Canadian Node Expert List | M22: 4418 | N22: 201700 | O22: 1477 | P22: curator
A23: Alec Kaisand | B23: akaisand | C23: Alec Kaisand | D23: 1067639 | E23: Current | F23: Massachusetts Natural Heritage & Endangered Species Program | G23: NHESP GIS Manager | L23: NatureServe Network Staff List | M23: 12 | N23: 0 | O23: 10
A24: Alan Rockefeller | B24: alan_rockefeller | C24: Alan Rockefeller | D24: 25945 | E24: No | H24: Fungi | I24: NF%|NL% | L24: MTNHP and MBP Expert List | M24: 28884 | N24: 300239 | O24: 6529 | P24: curator
A25: Alan Liang | B25: alanliang | C25: Alan Liang | D25: 2650187 | E25: No | H25: Lepidoptera | I25: IILE% | L25: MTNHP Expert List | M25: 1259 | N25: 124712 | O25: 105
A26: Dirk C. Albach | B26: albach | D26: 726060 | E26: No | H26: Veronica | I26: PDSCR% | J26: The world's foremost Veronica expert. | L26: MTNHP and MBP Expert List | M26: 1953 | N26: 202824 | O26: 1020 | P26: curator
A27: Alex Abair | B27: alex_abair | C27: Alex Abair | D27: 434305 | E27: No | H27: Lamiaceae (mints) | I27: PDLAM% | J27: Removed flag due to too many cultivated species. | L27: MTNHP and MBP Expert List | M27: 9343 | N27: 203899 | O27: 3331 | P27: curator
A28: Alex Harman | B28: alex_cicindela_guy | C28: Alex Harman | D28: 579740 | E28: No | F28: Santa Barbara Museum of Natural History | G28: Schlinger Chair of Entomology | H28: Coleoptera|Orthoptera|Lepidoptera | I28: IICOL%|IIORT%|IILE% | L28: Canadian Node Expert List; updated expertise on 5/9/25 to account for iNat profile update | M28: 11851 | N28: 233520 | O28: 4519 | P28: curator
A29: Alexandre Bergeron | B29: alexandre_bergeron | C29: Alexandre Bergeron | D29: 4366607 | E29: No | F29: University of Montreal | G29: Botanist | H29: Vascular Plants | I29: P% | K29: NWT | L29: Canadian Node Expert List | M29: 142 | N29: 1402 | O29: 130
A30: Ali Chaney | B30: alichaney | C30: Ali Chaney | D30: 1659821 | E30: Current | F30: Nevada Natural Heritage Program | L30: 2020 network survey on iNaturalist | M30: 39 | N30: 3 | O30: 27
A31: Allison Siemens Worsley | B31: allisonsw_nsc | C31: Allison | D31: 119123 | E31: Current | F31: NatureServe Canada | L31: 2020 network survey on iNaturalist | M31: 144 | N31: 20 | O31: 105 | P31: curator
A32: Al Schotz | B32: alschotz | C32: Al Schotz | D32: 406181 | E32: Current | F32: Alabama Natural Heritage Program | G32: Botanist | L32: NatureServe Network Staff List | M32: 191 | N32: 61 | O32: 179
A33: Alvan Buckley | B33: alvanbuckley | D33: 1513192 | E33: No | H33: General | I33: P%|A%|I% | K33: NF/LB | L33: Canadian Node Expert List | M33: 408 | N33: 538 | O33: 289
A34: Amaad Blades | B34: amaad_blades | D34: 7366982 | E34: Current | F34: Georgia Department of Natural Resources | G34: Wildlife Technician | H34: General | I34: P%|A%|I% | L34: 2024 Network Survey | M34: 244 | N34: 105 | O34: 212
A35: Amber Nguyen | B35: amber42836 | C35: Amber Nguyen | D35: 7443072 | E35: Current | F35: Michigan Natural Features Inventory | G35: Research Assistant | L35: NatureServe Network Staff List | M35: 0 | N35: 0 | O35: 0
A36: Andrew Meeds | B36: ameeds | C36: Andrew Meeds | D36: 917390 | E36: No | H36: Insects | I36: II% | L36: MBP Expert List | M36: 13262 | N36: 91187 | O36: 3770 | P36: curator
A37: Harpo Faust | B37: amen2stamens | C37: Harpo Faust | D37: 14828 | E37: No | F37: University of New Mexico | G37: Herbarium Manager | H37: Plants|Pteridophytes | I37: P% | L37: 2024 Network Survey | M37: 1650 | N37: 41 | O37: 1049
A38: Nathan Jones | B38: americanisopodologist | C38: Nathan T. Jones | D38: 1925317 | E38: No | H38: Isopods | I38: ICMAL% | J38: Currently writing a field guide to isopods of North America (both aquatic and terrestrial). https://www.americanisopodsmyriapods.com/taxonomic-guide-to-isopods-of-north-america | L38: Bryce Maxell bmaxell@mt.gov on 8/9/24. | M38: 15840 | N38: 92461 | O38: 1784 | P38: curator
A39: Amie Enns | B39: amieenns_nsc | C39: Amie Enns | D39: 114023 | E39: Current | F39: NatureServe Canada | G39: National Data Manager | L39: NatureServe Network Staff List | M39: 74 | N39: 696 | O39: 67
A40: Amy Buthod | B40: amybuthod | D40: 221999 | E40: Current | F40: Oklahoma Natural Heritage Inventory | G40: Botanical Specialist | H40: Plants | I40: P%|NB%|NA% | L40: NatureServe Network Staff List | M40: 564 | N40: 39356 | O40: 431
A41: Amy Jenkins | B41: amyjenkins | C41: Amy Jenkins | D41: 1360701 | E41: Current | F41: Florida Natural Areas Inventory | G41: Botanist | L41: NatureServe Network Staff List | M41: 52 | N41: 252 | O41: 48
A42: Andrew Dudley | B42: andrew_dudley | C42: Andrew Dudley | D42: 3788962 | E42: No | F42: Cactus enthusiast | H42: Cactaceae | I42: PDCAC% | L42: Bryce Maxell bmaxell@mt.gov on 6/4/25 | M42: 3916 | N42: 146991 | O42: 232 | P42: Curator
A43: Andrew Rohrbaugh | B43: andrewrohrbaugh | C43: Andrew Rohrbaugh | D43: 2904631 | E43: Current | F43: Pennsylvania Natural Heritage Program | G43: Botanist | L43: NatureServe Network Staff List | M43: 3 | N43: 1 | O43: 3
A44: Angie Schmidt | B44: angschmidt | C44: Angie Schmidt | D44: 255930 | E44: Current | F44: Idaho Natural Heritage Program | G44: Program Manager IFWIS | L44: NatureServe Network Staff List | M44: 70 | N44: 14 | O44: 55
A45: Sequoia Wrens | B45: aniedes | C45: Oonagh | D45: 2314302 | E45: No | H45: Isopods | I45: ICMAL% | J45: Currently writing a field guide to isopods of North America (both aquatic and terrestrial). https://www.americanisopodsmyriapods.com/taxonomic-guide-to-isopods-of-north-america | L45: Bryce Maxell bmaxell@mt.gov on 8/9/24. | M45: 2434 | N45: 14309 | O45: 916
A46: Anna Strong | B46: anna-0 | C46: anna strong | D46: 40156 | E46: Current | F46: Texas Parks and Wildlife Department Wildlife Diversity Branch | G46: Rare Species Botanist | L46: NatureServe Network Staff List | M46: 56 | N46: 125 | O46: 36 | P46: curator
A47: Anne Bowser | B47: annebowser | C47: Anne Bowser | D47: 319622 | E47: Current | F47: NatureServe | L47: NatureServe Staff List | M47: 4 | N47: 0 | O47: 4
A48: Annie Chang | B48: anniexchang | C48: Annie Chang | D48: 1283670 | E48: Current | F48: California Natural Diversity Database | G48: Environmental Scientist | L48: NatureServe Network Staff List | M48: 629 | N48: 0 | O48: 336
A49: Tony Romano | B49: anthonyromano | C49: Anthony Romano | D49: 169497 | E49: Current | F49: Office of Kentucky Nature Preserves | G49: Botanist | H49: Vascular Plants | I49: P% | L49: NatureServe Network Staff List | M49: 1051 | N49: 175 | O49: 819
A50: A. Smith | B50: apsmith10 | C50: A Smith | D50: 1868383 | E50: No | H50: Vascular Plants | I50: P% | L50: MTNHP Expert List | M50: 969 | N50: 1129 | O50: 498
A51: Aaron Schusteff | B51: arbonius | C51: Aaron Schusteff | D51: 748372 | E51: No | H51: General|Plants|Insects | I51: P%|A%|I% | L51: MBP Expert List | M51: 240 | N51: 2485 | O51: 160 | P51: curator
B52: arethusa | D52: 250191 | E52: No | H52: Vascular Plants|Orchidaceae|Carnivorous Plants | I52: P% | K52: SK, QC | L52: Canadian Node Expert List and MTNHP Expert List | M52: 965 | N52: 120886 | O52: 535 | P52: curator
A53: Patrick Alexander | B53: aspidoscelis | C53: Patrick Alexander | D53: 620642 | E53: No | F53: Bureau of Land Management | G53: Botanist | H53: Plants|Amphibians|Reptiles | I53: P%|AA%|AR% | J53: BLM Botanist/ecologist, expert in southern New Mexico flora | L53: 2024 Network Survey | M53: 12340 | N53: 88907 | O53: 2530 | P53: curator
A54: Sequoia Wrens | B54: astrobirder | C54: Sequoia Janirella Wrens | D54: 420537 | E54: No | H54: Isopods | I54: ICMAL% | J54: Currently writing a field guide to isopods of North America (both aquatic and terrestrial). https://www.americanisopodsmyriapods.com/taxonomic-guide-to-isopods-of-north-america | L54: 2024 Network Survey | M54: 152971 | N54: 41361 | O54: 12304
A55: Austin Baker | B55: austin_baker | C55: Austin Baker | D55: 1103606 | E55: No | H55: Insects, especially hymenoptera | I55: II% | L55: MBP Expert List | M55: 20 | N55: 3343 | O55: 19
A56: Austin Smith | B56: austinsmith | C56: Austin Smith | D56: 977825 | E56: No | H56: Barnacles | I56: ICCIR% | L56: MBP Expert List | M56: 5142 | N56: 108150 | O56: 1574 | P56: curator
A57: Ben Coulter | B57: b_coulter | D57: 15770 | E57: No | H57: Insects, flies, ants, jumping spiders | I57: II% | L57: MBP Expert List | M57: 3888 | N57: 16090 | O57: 2136 | P57: curator
A58: Stephanie Shelton | B58: badgerholefarm | C58: Stephanie Lee Shelton | D58: 1030733 | E58: Current | F58: Texas Parks and Wildlife Department Wildlife Diversity Branch | G58: TXNDD Data Manager | L58: NatureServe Network Staff List | M58: 25 | N58: 4 | O58: 18
A59: Barbara Parris | B59: barbaraparris | C59: Barbara Parris | D59: 355160 | E59: No | H59: Pteridophyts|Lycophytes | I59: PP% | L59: MBP Expert List | M59: 6941 | N59: 168670 | O59: 2053
A60: Bob Gottfried | B60: bayoubob70 | D60: 1173905 | E60: Current | F60: Texas Parks and Wildlife Department Wildlife Diversity Branch | G60: Natural Diversity Database Program Supervisor | L60: NatureServe Network Staff List | M60: 0 | N60: 0 | O60: 0
A61: Brandon Claridge | B61: bclaridge | C61: Brandon | D61: 1412462 | E61: No | H61: Ichnuemonidae | I61: IIHYM% | L61: MBP Expert List | M61: 335 | N61: 7385 | O61: 204
B62: bdagley | C62: bdagley | D62: 3069707 | E62: No | H62: Bees | I62: IIHYM% | L62: Added by Bryce Maxell bmaxell@mt.gov on 2/18/26 | M62: 7860 | N62: 745653 | O62: 1256
A63: Bastian Drolshagen | B63: bdrolshagen | C63: Bastian Drolshagen | D63: 4265031 | E63: No | H63: Spiders | I63: ILA% | L63: MTNHP Expert List | M63: 39 | N63: 18606 | O63: 30
A64: Brian Early | B64: bearly33 | C64: Brian-Sean Early | D64: 19411 | E64: Current | F64: Louisiana Wildlife Diversity Program | G64: Botanist | L64: NatureServe Network Staff List | M64: 2690 | N64: 7319 | O64: 1401
A65: Gary Beauvais | B65: beauvais | D65: 1449070 | E65: Current | F65: Wyoming Natural Diversity Database | G65: Director, WYNDD | H65: Vertebrates | I65: A% | L65: NatureServe Network Staff List | M65: 0 | N65: 0 | O65: 0
A66: Lincoln R. Best | B66: beesofcanada | C66: Lincoln R. Best | D66: 760776 | E66: No | H66: Bees | I66: IIHYM% | L66: Added by Bryce Maxell bmaxell@mt.gov on 2/18/26 | M66: 207 | N66: 875 | O66: 107
A67: Ben Ginter | B67: ben_ginter | C67: Ben Ginter | D67: 4055524 | E67: No | H67: Birds | I67: AB% | K67: YT | L67: Canadian Node Expert List | M67: 4203 | N67: 5003 | O67: 1103
A68: Ben Benton | B68: benbenton01 | C68: Ben Benton | D68: 393850 | E68: Current | F68: Arkansas Natural Heritage Commission | G68: Botanist | H68: Vascular Plants | I68: P% | L68: 2024 Network Survey | M68: 1148 | N68: 1130 | O68: 742
A69: Benoit Dorion | B69: benoitdorion | D69: 2170273 | E69: No | H69: Vascular Plants | I69: P% | K69: NB, NS, PE | L69: Canadian Node Expert List | M69: 931 | N69: 208 | O69: 588
A70: Bonnie Heidel | B70: bheidel | D70: 6047045 | E70: Current | F70: Wyoming Natural Diversity Database | G70: Lead Botanist | H70: Plants | I70: P%|NB%|NA% | L70: NatureServe Network Staff List | M70: 19 | N70: 0 | O70: 16
A71: Ryan Patrick | B71: biglaughinggym | C71: Ryan Patrick | D71: 1521683 | E71: No | H71: Fungi | I71: NF%|NL% | L71: MTNHP Expert List | M71: 212 | N71: 7359 | O71: 184
A72: Bill Nichols | B72: bill42 | C72: Bill Nichols | D72: 285865 | E72: Current | F72: New Hampshire Natural Heritage Bureau | G72: Ecologist/Botanist | L72: NatureServe Network Staff List | M72: 1 | N72: 0 | O72: 1
A73: Bill Hubick | B73: billhubick | C73: Bill Hubick | D73: 541847 | E73: No | H73: General | I73: P%|A%|I% | L73: MBP Expert List | M73: 143966 | N73: 314050 | O73: 7182 | P73: curator
A74: Bill Reynolds | B74: billreynolds | C74: William (Bill) Reynolds | D74: 12510 | E74: No | H74: Insects|esp. cicadas | I74: II% | L74: MBP Expert List | M74: 66 | N74: 7919 | O74: 32 | P74: curator
A75: Matt Boone | B75: birderboone | C75: Matt Boone | D75: 1165706 | E75: Current | F75: Idaho Natural Heritage Program | G75: Data Management Team Lead | L75: NatureServe Network Staff List | M75: 253 | N75: 105 | O75: 173
A76: Betsy Leppo | B76: bleppo | D76: 390529 | E76: Current | F76: Pennsylvania Natural Heritage Program | G76: Invertebrate Zoologist | L76: NatureServe Network Staff List | M76: 1697 | N76: 230 | O76: 1009
A77: Aaron Hunt | B77: blocky | D77: 452693 | E77: No | H77: Lepidoptera | I77: IILE% | K77: YT | L77: Canadian Node Expert List | M77: 2213 | N77: 19771 | O77: 841
A78: Bryan Tronstad | B78: bltronstad | D78: 7272508 | E78: Current | F78: Wyoming Natural Diversity Database | G78: Invertebrate Collections Manager and Taxonomist | H78: Insects|Bees | I78: II% | L78: 2024 Network Survey | M78: 0 | N78: 0 | O78: 0
A79: Blaine Mathison | B79: bmathison | C79: Blaine Mathison | D79: 1229743 | E79: No | H79: Coleoptera | I79: IICOL% | K79: NB, NS, PE | L79: Canadian Node Expert List and MTNHP Expert List | M79: 0 | N79: 48184 | O79: 0 | P79: curator
A80: Bryce Maxell | B80: bmaxell | C80: Bryce Maxell | D80: 237929 | E80: Current | F80: Montana Natural Heritage Program | G80: Program Coordinator | H80: Vertebrates|Noxious Weeds | I80: A%|PDAST2D020|PDBOR0D060|PDLYT090B0|PMIRI090T0|PDEUP0Q0L2|PDASTD2010|PDAST1Y060|PDTAM01080|PDCLU031A0|PDBRA0L020|PDBOR0B070|PDBRA0B010|IMGAS%|PDAST2E090|PMPOA151H0|PDCON05020|PDBOR0B070|PDSCR110F0|PDAST2E090|PDEUP0Q0L2|PDELG01010|PMPOA151H0|PDBOR0D060|PMIRI090T0|PDAST1Y140|PDAST4W0B0|PDEUP0Q0L2|PDSCR110F0|PDCON05020|PDAST4W0B0|PDAST2E090|PDAST4W090|PDAST5V040|PDAST1S040|PDAST92050|PDBRA0B010|PDASTD2010|PDNYM05090|PDAST2J040|AFCJB08010|PMBUT01010|PDAST8H1U0|PMORC17010|PDSOL0Z2C0|PDSOL0G020|PDDIP02010|IMGASD7030|PDBRA0B010|PDAST0J030|PDCAR0U200|PDBRA1B010|PDGER01040|IMGASD7030|IMGAS93050|PDMAL0R040 | L80: NatureServe Network Staff List | M80: 362 | N80: 4264 | O80: 167
A81: Bob Borth | B81: bob_borth | C81: Bob Borth | D81: 1105519 | E81: No | H81: Lepidoptera | I81: IILE% | J81: Especially Catocala | L81: MBP Expert List | M81: 7 | N81: 65933 | O81: 7
A82: Robert W. Harding | B82: bobharding | C82: Robert W. Harding | D82: 241853 | E82: No | H82: Odonata|Orthoptera|Amphibia|Reptilia | I82: IIODO%|IIORT%|AA%|AR% | K82: NB, NS, PE, YT, SK | L82: Canadian Node Expert List | M82: 18209 | N82: 37016 | O82: 3005
A83: Boaz Crees | B83: bocrees | D83: 6494296 | E83: Current | F83: Montana Natural Heritage Program | G83: Avian Specialist | H83: Birds | I83: AB% | L83: NatureServe Network Staff List and MBP Expert List | M83: 104 | N83: 11893 | O83: 86
A84: Bonnie Fournier | B84: bonny18 | C84: bonny fournier | D84: 5937713 | E84: Current | F84: Northwest Territories Conservation Data Centre | G84: GIS Analyst | L84: NatureServe Network Staff List | M84: 2 | N84: 0 | O84: 0
A85: Boris Büche | B85: borisb | D85: 180811 | E85: No | H85: Coleoptera | I85: IICOL% | K85: NB, NS, PE | L85: Canadian Node Expert List and MBP Expert List | M85: 0 | N85: 730043 | O85: 0 | P85: curator
A86: Owen Boyle | B86: botanizer | C86: Owen Boyle | D86: 2988 | E86: Current | F86: Wisconsin Natural Heritage Program | G86: Species Management Section Manager | L86: NatureServe Network Staff List | M86: 398 | N86: 234 | O86: 306
A87: Amanda Eberly | B87: botanygirl | D87: 5892 | E87: Current | F87: NatureServe | G87: Research Botanist | H87: Plants | I87: P%|NB%|NA% | L87: NatureServe Network Staff List and MBP Expert List | M87: 13225 | N87: 5436 | O87: 3934
A88: Roger McCoy | B88: botanyroger | C88: Roger McCoy | D88: 3102597 | E88: Current | F88: Tennessee Division of Natural Areas | G88: Director | L88: NatureServe Network Staff List | M88: 219 | N88: 23 | O88: 187
A89: Brad Lambert | B89: bradlambert | C89: brad lambert | D89: 3344980 | E89: Current | F89: Colorado Natural Heritage Program | G89: Zoologist | L89: NatureServe Network Staff List | M89: 5 | N89: 0 | O89: 5
A90: Bradley Rasmussen | B90: bradleyfishes | C90: Bradley Rasmussen | D90: 641347 | E90: No | H90: Fish | I90: AF% | K90: BC, YT | L90: Canadian Node Expert List | M90: 3533 | N90: 15124 | O90: 1660
A91: Brad Oberle | B91: bradoberle | C91: Brad Oberle | D91: 1344208 | E91: No | H91: Shooting Stars in the Genus Dodecatheon | I91: PDPRI% | L91: MTNHP Expert List | M91: 211 | N91: 2631 | O91: 153
A92: Brad Toms | B92: bradtoms | D92: 395601 | E92: No | F92: Mersey Tobeatic Research Institute | G92: Wildlife Biologist | H92: Amphibians|Reptiles|Lichens | I92: AA%|AR%|NL% | K92: BC, AB, YT, NF/LB | L92: Canadian Node Expert List | M92: 1253 | N92: 25076 | O92: 734
A93: Brandon Woo | B93: brandonwoo | C93: Brandon Woo | D93: 264861 | E93: No | F93: Texas A&M Univesity | G93: Graduate Student | H93: Orthoptera | I93: IIORT% | K93: NL | L93: Canadian Node Expert List and MBP Expert List | M93: 32669 | N93: 304871 | O93: 7506 | P93: curator
A94: Brenda L. Wichmann | B94: brendalwichmann | C94: Brenda L Wichmann | D94: 144560 | E94: Current | F94: North Carolina Natural Heritage Program | L94: 2020 network survey on iNaturalist | M94: 7 | N94: 10 | O94: 7
A95: Brent Baker | B95: brent_baker | C95: Brent Baker | D95: 1454925 | E95: Former | F95: Arkansas Natural Heritage Program | G95: Botanist | H95: Vascular Plants | I95: P% | J95: Gillenia, Hibiscus, Krigia, Liatris, Monarda, Streptanthus, Verbesina, and Vernonia | K95: US | L95: NatureServe Network Staff List | M95: 250 | N95: 140114 | O95: 216
A96: Brett Albanese | B96: brettalbanese | C96: Brett Albanese | D96: 3059536 | E96: Current | F96: Georgia Wildlife Conservation Section | G96: Program Manager, SWAP coordinator | L96: NatureServe Network Staff List | M96: 15 | N96: 0 | O96: 14
A97: Brevan Wagner | B97: brevan_wagner | C97: Brevan Wagner | D97: 4015883 | E97: No | F97: University of Alberta | G97: Graduate Student | H97: Lepidoptera | I97: IILE% | L97: Bryce Maxell bmaxell@mt.gov 1/22/26
A98: Brittney Miller | B98: brittney_the_botanist | C98: Brittney Miller | D98: 2649021 | E98: No | H98: Bryophytes | I98: NB% | K98: NB, NS, PE | L98: Canadian Node Expert List | M98: 1505 | N98: 4020 | O98: 716
A99: Norbert Sauberer | B99: brothernorbert | C99: Norbert Sauberer | D99: 2626695 | E99: No | H99: Vascular Plants | I99: P% | K99: NB, NS, PE | L99: Canadian Node Expert List | M99: 4735 | N99: 555667 | O99: 3101
A100: Bruce Young | B100: bruce | C100: Bruce Young | D100: 1413 | E100: Current | F100: NatureServe | G100: Zoologist | L100: NatureServe Staff List | M100: 359 | N100: 277 | O100: 242
...

Sheet Taxa_Not_Identifiable_w_Photos_
A1: Scientific Name | B1: Common Name | C1: Taxonomic Level | D1: Geographic Area of Revelance | E1: What is required to reliably determine species identification? | F1: Submitter Name | G1: Submitter Email
A2: Neotamias ruficaudus; Neotamias amoenus; Neotamias minimus | B2: Red-tailed chipmunk; Yellow-pine Chipmunk; Least Chipmunk | C2: Neotamias | D2: Mountainous areas of Northern Rockies where species co-occur | E2: Clean skeleton. Occasionally individuals can be identified based on pelage and detailed habitat but this is rare. | F2: Dan Bachen | G2: dbachen@mt.gov

Sheet Summary Statistics
B1: No_Observations | C1: No_Identifications | D1: No_Species | E1: No_Curators
A2: Overall
A3: Total | B3: =SUM(iNaturalist_Experts_US_Canada!M2:M742) -> 4239609 | C3: =SUM(iNaturalist_Experts_US_Canada!N2:N742) -> 29816516
A4: Count > 0 | B4: =COUNTIF(iNaturalist_Experts_US_Canada!M2:M742,">0") -> 678 | C4: =COUNTIF(iNaturalist_Experts_US_Canada!N2:N742,">0") -> 637 | D4: =COUNTIF(iNaturalist_Experts_US_Canada!O2:O742,">0") -> 671 | E4: =COUNTIF(iNaturalist_Experts_US_Canada!P2:P742,"Curator") -> 139
A5: Average | B5: =AVERAGE(iNaturalist_Experts_US_Canada!M2:M742) -> 5776.0341 | C5: =AVERAGE(iNaturalist_Experts_US_Canada!N2:N742) -> 40621.956 | D5: =AVERAGE(iNaturalist_Experts_US_Canada!O2:O742) -> 1109.1131
A7: Other Experts
A8: Total | B8: =SUM(iNaturalist_Experts_US_Canada!M333:M742) -> 2265105 | C8: =SUM(iNaturalist_Experts_US_Canada!N333:N742) -> 17308918
A9: Count > 0 | B9: =COUNTIF(iNaturalist_Experts_US_Canada!M333:M742,">0") -> 371 | C9: =COUNTIF(iNaturalist_Experts_US_Canada!N333:N742,">0") -> 346 | D9: =COUNTIF(iNaturalist_Experts_US_Canada!O333:O742,">0") -> 366 | E9: =COUNTIF(iNaturalist_Experts_US_Canada!P333:P742,"Curator") -> 73
A10: Average | B10: =AVERAGE(iNaturalist_Experts_US_Canada!M333:M742) -> 5579.0764 | C10: =AVERAGE(iNaturalist_Experts_US_Canada!N333:N742) -> 42632.803 | D10: =AVERAGE(iNaturalist_Experts_US_Canada!O333:O742) -> 1050.9434
A12: Current or Former NatureServe Network Staff
A13: Total | B13: =SUM(iNaturalist_Experts_US_Canada!M2:M331) -> 1973892 | C13: =SUM(iNaturalist_Experts_US_Canada!N2:N331) -> 12503573
A14: Count > 0 | B14: =COUNTIF(iNaturalist_Experts_US_Canada!M2:M331,">0") -> 306 | C14: =COUNTIF(iNaturalist_Experts_US_Canada!N2:N331,">0") -> 290 | D14: =COUNTIF(iNaturalist_Experts_US_Canada!O2:O331,">0") -> 304 | E14: =COUNTIF(iNaturalist_Experts_US_Canada!P2:P331,"Curator") -> 66
A15: Average | B15: =AVERAGE(iNaturalist_Experts_US_Canada!M2:M331) -> 6036.367 | C15: =AVERAGE(iNaturalist_Experts_US_Canada!N2:N331) -> 38237.226 | D15: =AVERAGE(iNaturalist_Experts_US_Canada!O2:O331) -> 1183.0612
A17: Count of Experts with Taxonomic Expertise Listed | B17: 460 of 717...so 257 network staff have iNaturalist accounts, but their expertise is not yet listed.
